{"results" : [
{"image_id": 1000006,
"image_url": "https://iiif.artresearch.net/iiif/2/zeri!129200%21128993_g.jpg/full/full/0/default.jpg",
"search_results": {"bounding_rects":[],"image_ids":[],"scores":[],"tags":[],"type":"SEARCH_RESULTS"} },
{"image_id": 1000007,
"image_url": "https://iiif.artresearch.net/iiif/2/zeri!129200%21128994_g.jpg/full/full/0/default.jpg",
"search_results": {"bounding_rects":[],"image_ids":[],"scores":[],"tags":[],"type":"SEARCH_RESULTS"} },
{"image_id": 1000008,
"image_url": "https://iiif.artresearch.net/iiif/2/zeri!128400%21128106_g.jpg/full/full/0/default.jpg",
"search_results": {"bounding_rects":[],"image_ids":[],"scores":[],"tags":[],"type":"SEARCH_RESULTS"} },
{"image_id": 1000009,
"image_url": "https://iiif.artresearch.net/iiif/2/zeri!129200%21129035_g.jpg/full/full/0/default.jpg",
"search_results": {"bounding_rects":[],"image_ids":[],"scores":[],"tags":[],"type":"SEARCH_RESULTS"} },
{"image_id": 1000010,
"image_url": "https://iiif.artresearch.net/iiif/2/zeri!127200%21127025_g.jpg/full/full/0/default.jpg",
"search_results": {"bounding_rects":[],"image_ids":[],"scores":[],"tags":[],"type":"SEARCH_RESULTS"} },
{}]}
